jupyter_viewer/__init__.py
jupyter_viewer/__main__.py
jupyter_viewer/_version.py
jupyter_viewer/serverapplication.py
jupyter_viewer/handlers/__init__.py
jupyter_viewer/handlers/base.py
jupyter_viewer/handlers/config/__init__.py
jupyter_viewer/handlers/config/handler.py
jupyter_viewer/handlers/index/__init__.py
jupyter_viewer/handlers/index/handler.py
jupyter_viewer/static/005bfbe85ee1ea60014b.svg
jupyter_viewer/static/00d3a96fd40b52f11e26.svg
jupyter_viewer/static/0b7bed8b8fd74e6cff0f.svg
jupyter_viewer/static/0bc952fba30b70f21f55.svg
jupyter_viewer/static/0c35296359e3f6f61911.svg
jupyter_viewer/static/1042ec7310f1904eef9f.svg
jupyter_viewer/static/1100.jupyter-viewer.js
jupyter_viewer/static/1109.jupyter-viewer.js
jupyter_viewer/static/1109.jupyter-viewer.js.LICENSE.txt
jupyter_viewer/static/1133.jupyter-viewer.js
jupyter_viewer/static/1164.jupyter-viewer.js
jupyter_viewer/static/1171.jupyter-viewer.js
jupyter_viewer/static/1175.jupyter-viewer.js
jupyter_viewer/static/11c006a5b5e50d73068a.svg
jupyter_viewer/static/1200.jupyter-viewer.js
jupyter_viewer/static/1208.jupyter-viewer.js
jupyter_viewer/static/1247.jupyter-viewer.js
jupyter_viewer/static/1379.jupyter-viewer.js
jupyter_viewer/static/1382.jupyter-viewer.js
jupyter_viewer/static/152.jupyter-viewer.js
jupyter_viewer/static/1551f4f60c37af51121f106501f69b80.woff2
jupyter_viewer/static/168.jupyter-viewer.js
jupyter_viewer/static/172.jupyter-viewer.js
jupyter_viewer/static/1815.jupyter-viewer.js
jupyter_viewer/static/1887.jupyter-viewer.js
jupyter_viewer/static/1893.jupyter-viewer.js
jupyter_viewer/static/18e91544007809992c96.svg
jupyter_viewer/static/192736b3558a617d0e64.svg
jupyter_viewer/static/1932.jupyter-viewer.js
jupyter_viewer/static/1938.jupyter-viewer.js
jupyter_viewer/static/1c2b261e145b94cf4df8.svg
jupyter_viewer/static/1d6210fb8b373d57adea.svg
jupyter_viewer/static/201f2b446f94618936b2.svg
jupyter_viewer/static/2034.jupyter-viewer.js
jupyter_viewer/static/210.jupyter-viewer.js
jupyter_viewer-1.0.3.dist-info/METADATA
jupyter_viewer-1.0.3.dist-info/WHEEL
jupyter_viewer-1.0.3.dist-info/entry_points.txt
jupyter_viewer-1.0.3.dist-info/licenses/LICENSE
jupyter_viewer-1.0.3.dist-info/RECORD
